Workbook

Sheet Resumen Ejecutivo
A1: NicaExport Trading, S.A. - Resumen Ejecutivo
A2: Resultados del análisis de 100 operaciones registradas durante el año 2026
A4: Nº | B4: Pregunta empresarial | C4: Respuesta | E4: Función condicional solicitada | F4: Resultado
A5: 1 | B5: ¿Cuántas operaciones internacionales se realizaron? | C5: =COUNTA(Operaciones!A4:A103) -> 100 | E5: Operaciones hacia EE.UU. | F5: =COUNTIFS(Operaciones!E4:E103,"EE.UU.") -> 20
A6: 2 | B6: ¿Cuántas operaciones están pendientes? | C6: =COUNTIFS(Operaciones!I4:I103,"Pendiente") -> 15 | E6: Operaciones pendientes | F6: =COUNTIFS(Operaciones!I4:I103,"Pendiente") -> 15
A7: 3 | B7: ¿Cuál es el país con mayor cantidad de operaciones? | C7: =IF(COUNTIF('Tablas y gráficos'!$Q$5:$Q$9,MAX('Tablas y gráficos'!$Q$5:$Q$9))>1,"Existe empate: "&COUNTIF('Tablas y gráficos'!$Q$5:$Q$9,MAX('Tablas y gráficos'!$Q$5:$Q$9))&" países tienen "&MAX('Tablas y gráficos'!$Q$5:$Q$9)&" operaciones.",INDEX('Tablas y gráficos'!$P$5:$P$9,MATCH(MAX('Tablas y gráficos'!$Q$5:$Q$9),'Tablas y gráficos'!$Q$5:$Q$9,0))&": "&MAX('Tablas y gráficos'!$Q$5:$Q$9)&" operaciones") -> Existe empate: 5 países tienen 20 operaciones. | E7: Valor FOB hacia México | F7: =SUMIFS(Operaciones!O4:O103,Operaciones!E4:E103,"México") -> 120313
A8: 4 | B8: ¿Cuál es el país que genera mayor valor FOB? | C8: =INDEX('Tablas y gráficos'!$A$5:$A$9,MATCH(MAX('Tablas y gráficos'!$B$5:$B$9),'Tablas y gráficos'!$B$5:$B$9,0))&": US$"&TEXT(MAX('Tablas y gráficos'!$B$5:$B$9),"#,##0") -> EE.UU.: US$168,745 | E8: Unidades hacia Guatemala | F8: =SUMIFS(Operaciones!F4:F103,Operaciones!E4:E103,"Guatemala") -> 17130
A9: 5 | B9: ¿Cuál es el producto más exportado por unidades? | C9: =INDEX('Tablas y gráficos'!$D$5:$D$9,MATCH(MAX('Tablas y gráficos'!$F$5:$F$9),'Tablas y gráficos'!$F$5:$F$9,0))&": "&TEXT(MAX('Tablas y gráficos'!$F$5:$F$9),"#,##0")&" unidades" -> Café especial: 26,180 unidades | E9: Valor FOB de Café especial a EE.UU. | F9: =SUMIFS(Operaciones!O4:O103,Operaciones!J4:J103,"Café especial",Operaciones!E4:E103,"EE.UU.") -> 52390
A10: 6 | B10: ¿Cuál es el producto que genera mayor utilidad? | C10: =INDEX('Tablas y gráficos'!$D$5:$D$9,MATCH(MAX('Tablas y gráficos'!$E$5:$E$9),'Tablas y gráficos'!$E$5:$E$9,0))&": US$"&TEXT(MAX('Tablas y gráficos'!$E$5:$E$9),"#,##0")&" de utilidad" -> Café especial: US$62,832 de utilidad | E10: Utilidad entregada en Centroamérica | F10: =SUMIFS(Operaciones!Q4:Q103,Operaciones!L4:L103,"Centroamérica",Operaciones!I4:I103,"Entregado") -> 33348
A11: 7 | B11: ¿Cuál es el mercado con mayor margen promedio? | C11: =INDEX('Tablas y gráficos'!$A$5:$A$9,MATCH(MAX('Tablas y gráficos'!$C$5:$C$9),'Tablas y gráficos'!$C$5:$C$9,0))&": "&TEXT(MAX('Tablas y gráficos'!$C$5:$C$9),"0.0%")&" de margen promedio" -> EE.UU.: 33.0% de margen promedio
A12: 8 | B12: ¿Cuántas operaciones tienen rentabilidad alta? | C12: =COUNTIFS(Operaciones!S4:S103,"Alta") -> 82 | E12: Datos académicos
A13: 9 | B13: ¿Cuánto se exportó hacia Centroamérica? | C13: =SUMIFS(Operaciones!O4:O103,Operaciones!L4:L103,"Centroamérica") -> 232879 | E13: Estudiante | F13: Octavio José Arana Sánchez
A14: 10 | B14: ¿Cuánto se exportó hacia Norteamérica? | C14: =SUMIFS(Operaciones!O4:O103,Operaciones!L4:L103,"Norteamérica") -> 289058 | E14: Carné | F14: 24011742
A15: 11 | B15: ¿Cuánto se exportó hacia Europa? | C15: =SUMIFS(Operaciones!O4:O103,Operaciones!L4:L103,"Europa") -> 136328 | E15: Docente | F15: César David Marín López
A16: 12 | B16: ¿Qué operaciones tienen prioridad comercial alta? | C16: =COUNTIFS(Operaciones!U4:U103,"Alta") -> 48 | E16: Asignatura | F16: Tecnologías de Gestión de Información
A17: 13 | B17: ¿Qué clientes generan mayor valor de exportación? | C17: =INDEX('Tablas y gráficos'!$M$5:$M$9,MATCH(MAX('Tablas y gráficos'!$N$5:$N$9),'Tablas y gráficos'!$N$5:$N$9,0))&": US$"&TEXT(MAX('Tablas y gráficos'!$N$5:$N$9),"#,##0") -> Global Foods: US$168,745 | E17: Grupo | F17: 7
A18: 14 | B18: ¿Qué operaciones requieren atención por estar pendientes? | C18: =COUNTIF(Operaciones!$I$4:$I$103,"Pendiente")&" operaciones. IDs listados en el bloque de atención." -> 15 operaciones. IDs listados en el bloque de atención.
A21: Conclusiones
A22: Hallazgo 1 | B22: EE.UU. lidera el valor FOB con US$168,745, equivalente al 25.6% del total.
A23: Hallazgo 2 | B23: Café especial lidera valor FOB y utilidad, con US$170,170 y US$62,832.
A24: Hallazgo 3 | B24: Norteamérica concentra US$289,058, el 43.9% del valor FOB total.
A25: Hallazgo 4 | B25: La cartera mantiene un margen ponderado de 32.5%. Maní procesado registra el margen más bajo, 28.1%.
A26: Hallazgo 5 | B26: Quince operaciones pendientes suman riesgo operativo y requieren seguimiento por fecha y cliente.
A29: Recomendaciones
A30: Recomendación 1 | B30: Concentrar la promoción de Café especial en EE.UU., mercado que ya aporta US$168,745 y mantiene el mayor margen por país.
A31: Recomendación 2 | B31: Corregir las 15 operaciones pendientes mediante seguimiento semanal con responsables y fechas de cierre.
A32: Recomendación 3 | B32: Revisar precio, costos y posicionamiento de Maní procesado, cuyo margen de 28.1% queda por debajo del resto de los productos.
A35: Operaciones pendientes
A36: EX004, EX012, EX019, EX025, EX032, EX039, EX046, EX052, EX059, EX065, EX072, EX079, EX085, EX089 y EX096 | B36: EX004, EX012, EX019, EX025, EX032, EX039, EX046, EX052, EX059, EX065, EX072, EX079, EX085, EX089 y EX096 | C36: EX004, EX012, EX019, EX025, EX032, EX039, EX046, EX052, EX059, EX065, EX072, EX079, EX085, EX089 y EX096 | D36: EX004, EX012, EX019, EX025, EX032, EX039, EX046, EX052, EX059, EX065, EX072, EX079, EX085, EX089 y EX096 | E36: EX004, EX012, EX019, EX025, EX032, EX039, EX046, EX052, EX059, EX065, EX072, EX079, EX085, EX089 y EX096 | F36: EX004, EX012, EX019, EX025, EX032, EX039, EX046, EX052, EX059, EX065, EX072, EX079, EX085, EX089 y EX096
E38: Funciones requeridas en la guía
E39: CONTAR.SI - Operaciones hacia EE.UU. | F39: =COUNTIF(Operaciones!$E$4:$E$103,"EE.UU.") -> 20
E40: SUMAR.SI - Valor FOB hacia México | F40: =SUMIF(Operaciones!$E$4:$E$103,"México",Operaciones!$O$4:$O$103) -> 120313
E41: SUMAR.SI.CONJUNTO - Café especial a EE.UU. | F41: =SUMIFS(Operaciones!$O$4:$O$103,Operaciones!$J$4:$J$103,"Café especial",Operaciones!$E$4:$E$103,"EE.UU.") -> 52390
E43: Observación de la base | F43: La fuente contiene operaciones de enero a diciembre de 2026 y no registra operaciones de El Salvador; se preservó la base sin inventar datos.

Sheet Tablas y gráficos
A1: Tablas dinámicas y gráficos analíticos
A2: Resúmenes formulares vinculados a Operaciones; se actualizan al cambiar los datos.
A4: País | B4: Valor FOB | C4: Margen promedio | D4: Producto | E4: Utilidad | F4: Unidades | G4: Región | H4: Valor FOB | J4: Prioridad | K4: Operaciones | M4: Cliente | N4: Valor FOB | P4: País | Q4: Operaciones
A5: EE.UU. | B5: =SUMIFS(Operaciones!$O$4:$O$103,Operaciones!$E$4:$E$103,$A5) -> 168745 | C5: =AVERAGEIFS(Operaciones!$R$4:$R$103,Operaciones!$E$4:$E$103,$A5) -> 0.33036728 | D5: Café especial | E5: =SUMIFS(Operaciones!$Q$4:$Q$103,Operaciones!$J$4:$J$103,$D5) -> 62832 | F5: =SUMIFS(Operaciones!$F$4:$F$103,Operaciones!$J$4:$J$103,$D5) -> 26180 | G5: Norteamérica | H5: =SUMIFS(Operaciones!$O$4:$O$103,Operaciones!$L$4:$L$103,$G5) -> 289058 | J5: Alta | K5: =COUNTIFS(Operaciones!$U$4:$U$103,$J5) -> 48 | M5: Global Foods | N5: =SUMIFS(Operaciones!$O$4:$O$103,Operaciones!$C$4:$C$103,$M5) -> 168745 | P5: =A5 -> EE.UU. | Q5: =COUNTIF(Operaciones!$E$4:$E$103,$P5) -> 20
A6: España | B6: =SUMIFS(Operaciones!$O$4:$O$103,Operaciones!$E$4:$E$103,$A6) -> 136328 | C6: =AVERAGEIFS(Operaciones!$R$4:$R$103,Operaciones!$E$4:$E$103,$A6) -> 0.32040424 | D6: Aceite de ajonjolí | E6: =SUMIFS(Operaciones!$Q$4:$Q$103,Operaciones!$J$4:$J$103,$D6) -> 42218 | F6: =SUMIFS(Operaciones!$F$4:$F$103,Operaciones!$J$4:$J$103,$D6) -> 11110 | G6: Centroamérica | H6: =SUMIFS(Operaciones!$O$4:$O$103,Operaciones!$L$4:$L$103,$G6) -> 232879 | J6: Media | K6: =COUNTIFS(Operaciones!$U$4:$U$103,$J6) -> 46 | M6: Comercial Maya | N6: =SUMIFS(Operaciones!$O$4:$O$103,Operaciones!$C$4:$C$103,$M6) -> 119335 | P6: =A6 -> España | Q6: =COUNTIF(Operaciones!$E$4:$E$103,$P6) -> 20
A7: México | B7: =SUMIFS(Operaciones!$O$4:$O$103,Operaciones!$E$4:$E$103,$A7) -> 120313 | C7: =AVERAGEIFS(Operaciones!$R$4:$R$103,Operaciones!$E$4:$E$103,$A7) -> 0.32960674 | D7: Miel natural | E7: =SUMIFS(Operaciones!$Q$4:$Q$103,Operaciones!$J$4:$J$103,$D7) -> 38688 | F7: =SUMIFS(Operaciones!$F$4:$F$103,Operaciones!$J$4:$J$103,$D7) -> 24180 | G7: Europa | H7: =SUMIFS(Operaciones!$O$4:$O$103,Operaciones!$L$4:$L$103,$G7) -> 136328 | J7: Baja | K7: =COUNTIFS(Operaciones!$U$4:$U$103,$J7) -> 6 | M7: Distribuidora Tica | N7: =SUMIFS(Operaciones!$O$4:$O$103,Operaciones!$C$4:$C$103,$M7) -> 113544 | P7: =A7 -> México | Q7: =COUNTIF(Operaciones!$E$4:$E$103,$P7) -> 20
A8: Guatemala | B8: =SUMIFS(Operaciones!$O$4:$O$103,Operaciones!$E$4:$E$103,$A8) -> 119335 | C8: =AVERAGEIFS(Operaciones!$R$4:$R$103,Operaciones!$E$4:$E$103,$A8) -> 0.32593014 | D8: Cacao en grano | E8: =SUMIFS(Operaciones!$Q$4:$Q$103,Operaciones!$J$4:$J$103,$D8) -> 36800 | F8: =SUMIFS(Operaciones!$F$4:$F$103,Operaciones!$J$4:$J$103,$D8) -> 16000 | M8: Iberia Foods | N8: =SUMIFS(Operaciones!$O$4:$O$103,Operaciones!$C$4:$C$103,$M8) -> 136328 | P8: =A8 -> Guatemala | Q8: =COUNTIF(Operaciones!$E$4:$E$103,$P8) -> 20
A9: Costa Rica | B9: =SUMIFS(Operaciones!$O$4:$O$103,Operaciones!$E$4:$E$103,$A9) -> 113544 | C9: =AVERAGEIFS(Operaciones!$R$4:$R$103,Operaciones!$E$4:$E$103,$A9) -> 0.3204958 | D9: Maní procesado | E9: =SUMIFS(Operaciones!$Q$4:$Q$103,Operaciones!$J$4:$J$103,$D9) -> 33534 | F9: =SUMIFS(Operaciones!$F$4:$F$103,Operaciones!$J$4:$J$103,$D9) -> 14580 | M9: Comercial Azteca | N9: =SUMIFS(Operaciones!$O$4:$O$103,Operaciones!$C$4:$C$103,$M9) -> 120313 | P9: =A9 -> Costa Rica | Q9: =COUNTIF(Operaciones!$E$4:$E$103,$P9) -> 20
G30: Interpretación de gráficos
G31: País | H31: EE.UU. encabeza el valor FOB. Los cinco países tienen el mismo número de operaciones, pero difieren en valor.
G32: Producto | H32: Café especial genera la mayor utilidad; Maní procesado registra la menor entre los cinco productos.
G33: Región | H33: Norteamérica aporta US$289,058 y supera a Centroamérica y Europa.

Sheet Tablas dinámicas
A1: Tablas dinámicas del análisis de comercio internacional
A3: 1. Valor FOB por país | G3: 2. Utilidad por producto
A4: Etiquetas de fila | B4: Suma de Valor FOB | G4: Etiquetas de fila | H4: Utilidad total
A5: Costa Rica | B5: 113544 | G5: Aceite de ajonjolí | H5: 42218
A6: EE.UU. | B6: 168745 | G6: Cacao en grano | H6: 36800
A7: España | B7: 136328 | G7: Café especial | H7: 62832
A8: Guatemala | B8: 119335 | G8: Maní procesado | H8: 33534
A9: México | B9: 120313 | G9: Miel natural | H9: 38688
A10: Total general | B10: 658265 | G10: Total general | H10: 214072
A17: 3. Valor FOB por región | G17: 4. Operaciones por prioridad
A18: Etiquetas de fila | B18: Valor FOB total | G18: Etiquetas de fila | H18: Cantidad de operaciones
A19: Centroamérica | B19: 232879 | G19: Alta | H19: 48
A20: Europa | B20: 136328 | G20: Baja | H20: 6
A21: Norteamérica | B21: 289058 | G21: Media | H21: 46
A22: Total general | B22: 658265 | G22: Total general | H22: 100

Sheet Operaciones
A1: NicaExport Trading, S.A. - Análisis de operaciones
A2: Datos base y cálculos empresariales. Las columnas J:N utilizan BUSCARV contra los catálogos.
A3: ID_Operación | B3: Fecha | C3: Cliente | D3: Código Producto | E3: País Destino | F3: Unidades | G3: Precio FOB | H3: Costo Unitario | I3: Estado | J3: Producto | K3: Categoría | L3: Región | M3: Arancel % | N3: Clasificación mercado | O3: Valor FOB | P3: Costo total | Q3: Utilidad | R3: Margen | S3: Nivel rentabilidad | T3: Nivel operación | U3: Prioridad comercial
A4: EX001 | B4: 46027 | C4: Comercial Maya | D4: P003 | E4: Guatemala | F4: 850 | G4: 4.8 | H4: 3.2 | I4: Embarcado | J4: =VLOOKUP(D4,Productos!$A$4:$D$8,2,FALSE) -> Miel natural | K4: =VLOOKUP(D4,Productos!$A$4:$D$8,3,FALSE) -> Apícola | L4: =VLOOKUP(E4,Mercados!$A$4:$D$9,2,FALSE) -> Centroamérica | M4: =VLOOKUP(E4,Mercados!$A$4:$D$9,3,FALSE) -> 0.03 | N4: =VLOOKUP(E4,Mercados!$A$4:$D$9,4,FALSE) -> Estratégico | O4: =F4*G4 -> 4080 | P4: =F4*H4 -> 2720 | Q4: =O4-P4 -> 1360 | R4: =Q4/O4 -> 0.33333333 | S4: =IF(R4>=30%,"Alta",IF(R4>=15%,"Media","Baja")) -> Alta | T4: =IF(O4>=10000,"Grande",IF(O4>=5000,"Mediana","Pequeña")) -> Pequeña | U4: =IF(AND(N4="Estratégico",R4>=30%),"Alta",IF(AND(N4="Estratégico",R4<30%),"Media",IF(AND(N4="Potencial",R4>=30%),"Media","Baja"))) -> Alta
A5: EX002 | B5: 46034 | C5: Global Foods | D5: P001 | E5: EE.UU. | F5: 1200 | G5: 6.5 | H5: 4.1 | I5: Entregado | J5: =VLOOKUP(D5,Productos!$A$4:$D$8,2,FALSE) -> Café especial | K5: =VLOOKUP(D5,Productos!$A$4:$D$8,3,FALSE) -> Café | L5: =VLOOKUP(E5,Mercados!$A$4:$D$9,2,FALSE) -> Norteamérica | M5: =VLOOKUP(E5,Mercados!$A$4:$D$9,3,FALSE) -> 0.05 | N5: =VLOOKUP(E5,Mercados!$A$4:$D$9,4,FALSE) -> Estratégico | O5: =F5*G5 -> 7800 | P5: =F5*H5 -> 4920 | Q5: =O5-P5 -> 2880 | R5: =Q5/O5 -> 0.36923077 | S5: =IF(R5>=30%,"Alta",IF(R5>=15%,"Media","Baja")) -> Alta | T5: =IF(O5>=10000,"Grande",IF(O5>=5000,"Mediana","Pequeña")) -> Mediana | U5: =IF(AND(N5="Estratégico",R5>=30%),"Alta",IF(AND(N5="Estratégico",R5<30%),"Media",IF(AND(N5="Potencial",R5>=30%),"Media","Baja"))) -> Alta
A6: EX003 | B6: 46042 | C6: Distribuidora Tica | D6: P004 | E6: Costa Rica | F6: 650 | G6: 8.2 | H6: 5.9 | I6: Embarcado | J6: =VLOOKUP(D6,Productos!$A$4:$D$8,2,FALSE) -> Maní procesado | K6: =VLOOKUP(D6,Productos!$A$4:$D$8,3,FALSE) -> Semillas | L6: =VLOOKUP(E6,Mercados!$A$4:$D$9,2,FALSE) -> Centroamérica | M6: =VLOOKUP(E6,Mercados!$A$4:$D$9,3,FALSE) -> 0.02 | N6: =VLOOKUP(E6,Mercados!$A$4:$D$9,4,FALSE) -> Estratégico | O6: =F6*G6 -> 5330 | P6: =F6*H6 -> 3835 | Q6: =O6-P6 -> 1495 | R6: =Q6/O6 -> 0.2804878 | S6: =IF(R6>=30%,"Alta",IF(R6>=15%,"Media","Baja")) -> Media | T6: =IF(O6>=10000,"Grande",IF(O6>=5000,"Mediana","Pequeña")) -> Mediana | U6: =IF(AND(N6="Estratégico",R6>=30%),"Alta",IF(AND(N6="Estratégico",R6<30%),"Media",IF(AND(N6="Potencial",R6>=30%),"Media","Baja"))) -> Media
A7: EX004 | B7: 46056 | C7: Iberia Foods | D7: P002 | E7: España | F7: 950 | G7: 7.1 | H7: 4.8 | I7: Pendiente | J7: =VLOOKUP(D7,Productos!$A$4:$D$8,2,FALSE) -> Cacao en grano | K7: =VLOOKUP(D7,Productos!$A$4:$D$8,3,FALSE) -> Cacao | L7: =VLOOKUP(E7,Mercados!$A$4:$D$9,2,FALSE) -> Europa | M7: =VLOOKUP(E7,Mercados!$A$4:$D$9,3,FALSE) -> 0.1 | N7: =VLOOKUP(E7,Mercados!$A$4:$D$9,4,FALSE) -> Potencial | O7: =F7*G7 -> 6745 | P7: =F7*H7 -> 4560 | Q7: =O7-P7 -> 2185 | R7: =Q7/O7 -> 0.32394366 | S7: =IF(R7>=30%,"Alta",IF(R7>=15%,"Media","Baja")) -> Alta | T7: =IF(O7>=10000,"Grande",IF(O7>=5000,"Mediana","Pequeña")) -> Mediana | U7: =IF(AND(N7="Estratégico",R7>=30%),"Alta",IF(AND(N7="Estratégico",R7<30%),"Media",IF(AND(N7="Potencial",R7>=30%),"Media","Baja"))) -> Media
A8: EX005 | B8: 46068 | C8: Comercial Azteca | D8: P005 | E8: México | F8: 500 | G8: 12.5 | H8: 8.7 | I8: Entregado | J8: =VLOOKUP(D8,Productos!$A$4:$D$8,2,FALSE) -> Aceite de ajonjolí | K8: =VLOOKUP(D8,Productos!$A$4:$D$8,3,FALSE) -> Aceites | L8: =VLOOKUP(E8,Mercados!$A$4:$D$9,2,FALSE) -> Norteamérica | M8: =VLOOKUP(E8,Mercados!$A$4:$D$9,3,FALSE) -> 0.08 | N8: =VLOOKUP(E8,Mercados!$A$4:$D$9,4,FALSE) -> Potencial | O8: =F8*G8 -> 6250 | P8: =F8*H8 -> 4350 | Q8: =O8-P8 -> 1900 | R8: =Q8/O8 -> 0.304 | S8: =IF(R8>=30%,"Alta",IF(R8>=15%,"Media","Baja")) -> Alta | T8: =IF(O8>=10000,"Grande",IF(O8>=5000,"Mediana","Pequeña")) -> Mediana | U8: =IF(AND(N8="Estratégico",R8>=30%),"Alta",IF(AND(N8="Estratégico",R8<30%),"Media",IF(AND(N8="Potencial",R8>=30%),"Media","Baja"))) -> Media
A9: EX006 | B9: 46081 | C9: Global Foods | D9: P003 | E9: EE.UU. | F9: 1400 | G9: 4.8 | H9: 3.2 | I9: Entregado | J9: =VLOOKUP(D9,Productos!$A$4:$D$8,2,FALSE) -> Miel natural | K9: =VLOOKUP(D9,Productos!$A$4:$D$8,3,FALSE) -> Apícola | L9: =VLOOKUP(E9,Mercados!$A$4:$D$9,2,FALSE) -> Norteamérica | M9: =VLOOKUP(E9,Mercados!$A$4:$D$9,3,FALSE) -> 0.05 | N9: =VLOOKUP(E9,Mercados!$A$4:$D$9,4,FALSE) -> Estratégico | O9: =F9*G9 -> 6720 | P9: =F9*H9 -> 4480 | Q9: =O9-P9 -> 2240 | R9: =Q9/O9 -> 0.33333333 | S9: =IF(R9>=30%,"Alta",IF(R9>=15%,"Media","Baja")) -> Alta | T9: =IF(O9>=10000,"Grande",IF(O9>=5000,"Mediana","Pequeña")) -> Mediana | U9: =IF(AND(N9="Estratégico",R9>=30%),"Alta",IF(AND(N9="Estratégico",R9<30%),"Media",IF(AND(N9="Potencial",R9>=30%),"Media","Baja"))) -> Alta
A10: EX007 | B10: 46089 | C10: Distribuidora Tica | D10: P001 | E10: Costa Rica | F10: 900 | G10: 6.5 | H10: 4.1 | I10: Embarcado | J10: =VLOOKUP(D10,Productos!$A$4:$D$8,2,FALSE) -> Café especial | K10: =VLOOKUP(D10,Productos!$A$4:$D$8,3,FALSE) -> Café | L10: =VLOOKUP(E10,Mercados!$A$4:$D$9,2,FALSE) -> Centroamérica | M10: =VLOOKUP(E10,Mercados!$A$4:$D$9,3,FALSE) -> 0.02 | N10: =VLOOKUP(E10,Mercados!$A$4:$D$9,4,FALSE) -> Estratégico | O10: =F10*G10 -> 5850 | P10: =F10*H10 -> 3690 | Q10: =O10-P10 -> 2160 | R10: =Q10/O10 -> 0.36923077 | S10: =IF(R10>=30%,"Alta",IF(R10>=15%,"Media","Baja")) -> Alta | T10: =IF(O10>=10000,"Grande",IF(O10>=5000,"Mediana","Pequeña")) -> Mediana | U10: =IF(AND(N10="Estratégico",R10>=30%),"Alta",IF(AND(N10="Estratégico",R10<30%),"Media",IF(AND(N10="Potencial",R10>=30%),"Media","Baja"))) -> Alta
A11: EX008 | B11: 46099 | C11: Comercial Maya | D11: P004 | E11: Guatemala | F11: 750 | G11: 8.2 | H11: 5.9 | I11: Entregado | J11: =VLOOKUP(D11,Productos!$A$4:$D$8,2,FALSE) -> Maní procesado | K11: =VLOOKUP(D11,Productos!$A$4:$D$8,3,FALSE) -> Semillas | L11: =VLOOKUP(E11,Mercados!$A$4:$D$9,2,FALSE) -> Centroamérica | M11: =VLOOKUP(E11,Mercados!$A$4:$D$9,3,FALSE) -> 0.03 | N11: =VLOOKUP(E11,Mercados!$A$4:$D$9,4,FALSE) -> Estratégico | O11: =F11*G11 -> 6150 | P11: =F11*H11 -> 4425 | Q11: =O11-P11 -> 1725 | R11: =Q11/O11 -> 0.2804878 | S11: =IF(R11>=30%,"Alta",IF(R11>=15%,"Media","Baja")) -> Media | T11: =IF(O11>=10000,"Grande",IF(O11>=5000,"Mediana","Pequeña")) -> Mediana | U11: =IF(AND(N11="Estratégico",R11>=30%),"Alta",IF(AND(N11="Estratégico",R11<30%),"Media",IF(AND(N11="Potencial",R11>=30%),"Media","Baja"))) -> Media
A12: EX009 | B12: 46106 | C12: Iberia Foods | D12: P005 | E12: España | F12: 600 | G12: 12.5 | H12: 8.7 | I12: Embarcado | J12: =VLOOKUP(D12,Productos!$A$4:$D$8,2,FALSE) -> Aceite de ajonjolí | K12: =VLOOKUP(D12,Productos!$A$4:$D$8,3,FALSE) -> Aceites | L12: =VLOOKUP(E12,Mercados!$A$4:$D$9,2,FALSE) -> Europa | M12: =VLOOKUP(E12,Mercados!$A$4:$D$9,3,FALSE) -> 0.1 | N12: =VLOOKUP(E12,Mercados!$A$4:$D$9,4,FALSE) -> Potencial | O12: =F12*G12 -> 7500 | P12: =F12*H12 -> 5220 | Q12: =O12-P12 -> 2280 | R12: =Q12/O12 -> 0.304 | S12: =IF(R12>=30%,"Alta",IF(R12>=15%,"Media","Baja")) -> Alta | T12: =IF(O12>=10000,"Grande",IF(O12>=5000,"Mediana","Pequeña")) -> Mediana | U12: =IF(AND(N12="Estratégico",R12>=30%),"Alta",IF(AND(N12="Estratégico",R12<30%),"Media",IF(AND(N12="Potencial",R12>=30%),"Media","Baja"))) -> Media
A13: EX010 | B13: 46114 | C13: Comercial Azteca | D13: P002 | E13: México | F13: 1100 | G13: 7.1 | H13: 4.8 | I13: Entregado | J13: =VLOOKUP(D13,Productos!$A$4:$D$8,2,FALSE) -> Cacao en grano | K13: =VLOOKUP(D13,Productos!$A$4:$D$8,3,FALSE) -> Cacao | L13: =VLOOKUP(E13,Mercados!$A$4:$D$9,2,FALSE) -> Norteamérica | M13: =VLOOKUP(E13,Mercados!$A$4:$D$9,3,FALSE) -> 0.08 | N13: =VLOOKUP(E13,Mercados!$A$4:$D$9,4,FALSE) -> Potencial | O13: =F13*G13 -> 7810 | P13: =F13*H13 -> 5280 | Q13: =O13-P13 -> 2530 | R13: =Q13/O13 -> 0.32394366 | S13: =IF(R13>=30%,"Alta",IF(R13>=15%,"Media","Baja")) -> Alta | T13: =IF(O13>=10000,"Grande",IF(O13>=5000,"Mediana","Pequeña")) -> Mediana | U13: =IF(AND(N13="Estratégico",R13>=30%),"Alta",IF(AND(N13="Estratégico",R13<30%),"Media",IF(AND(N13="Potencial",R13>=30%),"Media","Baja"))) -> Media
A14: EX011 | B14: 46122 | C14: Global Foods | D14: P004 | E14: EE.UU. | F14: 1300 | G14: 8.2 | H14: 5.9 | I14: Entregado | J14: =VLOOKUP(D14,Productos!$A$4:$D$8,2,FALSE) -> Maní procesado | K14: =VLOOKUP(D14,Productos!$A$4:$D$8,3,FALSE) -> Semillas | L14: =VLOOKUP(E14,Mercados!$A$4:$D$9,2,FALSE) -> Norteamérica | M14: =VLOOKUP(E14,Mercados!$A$4:$D$9,3,FALSE) -> 0.05 | N14: =VLOOKUP(E14,Mercados!$A$4:$D$9,4,FALSE) -> Estratégico | O14: =F14*G14 -> 10660 | P14: =F14*H14 -> 7670 | Q14: =O14-P14 -> 2990 | R14: =Q14/O14 -> 0.2804878 | S14: =IF(R14>=30%,"Alta",IF(R14>=15%,"Media","Baja")) -> Media | T14: =IF(O14>=10000,"Grande",IF(O14>=5000,"Mediana","Pequeña")) -> Grande | U14: =IF(AND(N14="Estratégico",R14>=30%),"Alta",IF(AND(N14="Estratégico",R14<30%),"Media",IF(AND(N14="Potencial",R14>=30%),"Media","Baja"))) -> Media
A15: EX012 | B15: 46130 | C15: Comercial Maya | D15: P001 | E15: Guatemala | F15: 700 | G15: 6.5 | H15: 4.1 | I15: Pendiente | J15: =VLOOKUP(D15,Productos!$A$4:$D$8,2,FALSE) -> Café especial | K15: =VLOOKUP(D15,Productos!$A$4:$D$8,3,FALSE) -> Café | L15: =VLOOKUP(E15,Mercados!$A$4:$D$9,2,FALSE) -> Centroamérica | M15: =VLOOKUP(E15,Mercados!$A$4:$D$9,3,FALSE) -> 0.03 | N15: =VLOOKUP(E15,Mercados!$A$4:$D$9,4,FALSE) -> Estratégico | O15: =F15*G15 -> 4550 | P15: =F15*H15 -> 2870 | Q15: =O15-P15 -> 1680 | R15: =Q15/O15 -> 0.36923077 | S15: =IF(R15>=30%,"Alta",IF(R15>=15%,"Media","Baja")) -> Alta | T15: =IF(O15>=10000,"Grande",IF(O15>=5000,"Mediana","Pequeña")) -> Pequeña | U15: =IF(AND(N15="Estratégico",R15>=30%),"Alta",IF(AND(N15="Estratégico",R15<30%),"Media",IF(AND(N15="Potencial",R15>=30%),"Media","Baja"))) -> Alta
... A103: EX100 | B103: 46150 | C103: Comercial Azteca | D103: P001 | E103: México | F103: 1170 | G103: 6.5 | H103: 4.1 | I103: Entregado | J103: =VLOOKUP(D103,Productos!$A$4:$D$8,2,FALSE) -> Café especial | K103: =VLOOKUP(D103,Productos!$A$4:$D$8,3,FALSE) -> Café | L103: =VLOOKUP(E103,Mercados!$A$4:$D$9,2,FALSE) -> Norteamérica | M103: =VLOOKUP(E103,Mercados!$A$4:$D$9,3,FALSE) -> 0.08 | N103: =VLOOKUP(E103,Mercados!$A$4:$D$9,4,FALSE) -> Potencial | O103: =F103*G103 -> 7605 | P103: =F103*H103 -> 4797 | Q103: =O103-P103 -> 2808 | R103: =Q103/O103 -> 0.36923077 | S103: =IF(R103>=30%,"Alta",IF(R103>=15%,"Media","Baja")) -> Alta | T103: =IF(O103>=10000,"Grande",IF(O103>=5000,"Mediana","Pequeña")) -> Mediana | U103: =IF(AND(N103="Estratégico",R103>=30%),"Alta",IF(AND(N103="Estratégico",R103<30%),"Media",IF(AND(N103="Potencial",R103>=30%),"Media","Baja"))) -> Media
A105: Fuente: Caso de Estudio NicaExport Trading, S.A. y archivo de operaciones suministrado por la asignatura.

Sheet Productos
A1: Catálogo de productos
A3: Código | B3: Producto | C3: Categoría | D3: Unidad de Medida
A4: P001 | B4: Café especial | C4: Café | D4: Kg
A5: P002 | B5: Cacao en grano | C5: Cacao | D5: Kg
A6: P003 | B6: Miel natural | C6: Apícola | D6: Kg
A7: P004 | B7: Maní procesado | C7: Semillas | D7: Kg
A8: P005 | B8: Aceite de ajonjolí | C8: Aceites | D8: Litro

Sheet Mercados
A1: Catálogo de mercados
A3: País | B3: Región | C3: Arancel % | D3: Clasificación
A4: EE.UU. | B4: Norteamérica | C4: 0.05 | D4: Estratégico
A5: México | B5: Norteamérica | C5: 0.08 | D5: Potencial
A6: Guatemala | B6: Centroamérica | C6: 0.03 | D6: Estratégico
A7: Costa Rica | B7: Centroamérica | C7: 0.02 | D7: Estratégico
A8: El Salvador | B8: Centroamérica | C8: 0.02 | D8: Potencial
A9: España | B9: Europa | C9: 0.1 | D9: Potencial
